sanic_api/__init__.py
sanic_api/app.py
sanic_api/api/__init__.py
sanic_api/api/error.py
sanic_api/api/model.py
sanic_api/api/request.py
sanic_api/config/__init__.py
sanic_api/config/setting.py
sanic_api/logger/__init__.py
sanic_api/logger/config.py
sanic_api/logger/extension.py
sanic_api/openapi/__init__.py
sanic_api/openapi/extension.py
sanic_api/utils/__init__.py
sanic_api/utils/enum.py
sanic_api-0.5.2.dist-info/METADATA
sanic_api-0.5.2.dist-info/WHEEL
sanic_api-0.5.2.dist-info/entry_points.txt
sanic_api-0.5.2.dist-info/licenses/LICENSE.txt
sanic_api-0.5.2.dist-info/RECORD
