Metadata-Version: 2.4
Name: sanic-api
Version: 0.5.2
Summary: Sanic 框架实用API工具集，拥有自动生成文档、参数校验、配置的导入、日志功能的优化等功能，更好的助力接口的开发
Project-URL: homepage, https://github.com/x-haose/sanic-api
Project-URL: repository, https://github.com/x-haose/sanic-api
Project-URL: documentation, https://github.com/x-haose/sanic-api
Author-email: 昊色居士 <xhrtxh@gmail.com>
License-Expression: MIT
License-File: LICENSE.txt
Keywords: Sanic,Sanic扩展,异步
Classifier: Development Status :: 4 - Beta
Classifier: Intended Audience :: Developers
Classifier: License :: OSI Approved :: MIT License
Classifier: Operating System :: MacOS :: MacOS X
Classifier: Operating System :: Microsoft :: Windows
Classifier: Operating System :: POSIX :: BSD
Classifier: Operating System :: POSIX :: Linux
Classifier: Programming Language :: Python :: 3.10
Classifier: Programming Language :: Python :: 3.11
Classifier: Programming Language :: Python :: 3.12
Classifier: Programming Language :: Python :: 3.13
Classifier: Topic :: Internet :: WWW/HTTP
Classifier: Topic :: Software Development :: Libraries :: Application Frameworks
Classifier: Topic :: Software Development :: Libraries :: Python Modules
Requires-Python: >=3.10
Requires-Dist: hs-config==0.1.3
Requires-Dist: loguru>=0.7.2
Requires-Dist: loki-logger-handler>=0.1.4
Requires-Dist: orjson>=3.8.6
Requires-Dist: requests>=2.32.0
Requires-Dist: sanic-ext>=23.12.0
Requires-Dist: sanic>=24.12.0
Requires-Dist: sentry-sdk>=2.17.0
Requires-Dist: ujson>=5.7.0
